Metadata-Version: 2.1
Name: InfoTransIO
Version: 0.0.3
Summary: Transmit data using python with InfoTransIO
Home-page: https://sites.google.com/rayes.com.br/rafael-rayes/
Author: Rafael Rayes
Author-email: rafa@rayes.com.br
License: UNKNOWN
Platform: UNKNOWN
Classifier: Programming Language :: Python :: 3
Classifier: License :: OSI Approved :: MIT License
Classifier: Operating System :: OS Independent
